{
  "@context": [
    "https://www.w3.org/ns/activitystreams",
    "https://w3id.org/security/v1"
  ],
  "type": "Application",
  "id": "https://bsky.brid.gy/bsky.brid.gy",
  "url": [
    "https://fed.brid.gy/",
    "https://bsky.brid.gy/"
  ],
  "preferredUsername": "bsky.brid.gy",
  "summary": "<p><a href='https://fed.brid.gy/'>Bridgy Fed</a> bot user for <a href='https://bsky.social/'>Bluesky</a>. To bridge your fediverse account to Bluesky, follow this account or reply <em>yes</em> if it prompts you with a DM. <a href='https://fed.brid.gy/docs'>More info here.</a></p> <p>After you follow this account, it will follow you back. Accept its follow to make sure your fediverse posts get sent to the bridge and make it into Bluesky.</p>",
  "name": "Bridgy Fed for Bluesky",
  "image": [
    {
      "type": "Image",
      "url": "https://fed.brid.gy/static/bridgy_fed_banner.png"
    },
    {
      "name": "Bridgy Fed for Bluesky",
      "type": "Image",
      "url": "https://fed.brid.gy/static/bridgy_logo_square.jpg"
    }
  ],
  "icon": {
    "name": "Bridgy Fed for Bluesky",
    "type": "Image",
    "url": "https://fed.brid.gy/static/bridgy_logo_square.jpg"
  }
}
